setup.py
src/lujxdemo/__init__.py
src/lujxdemo/lgplib.py
src/lujxdemo/lujxdemo.py
src/lujxdemo.egg-info/PKG-INFO
src/lujxdemo.egg-info/SOURCES.txt
src/lujxdemo.egg-info/dependency_links.txt
src/lujxdemo.egg-info/top_level.txt