Metadata-Version: 1.2
Name: lujxdemo
Version: 0.0.3
Summary: library 
Home-page: http://10.177.132.101
Author: Lujx
Author-email: 20920139@qq.com
License: MIT Licence
Keywords: testing testautomation
Platform: any
Requires-Python: >=3.6.*
